apikeeper/__init__.py
apikeeper-0.0.1.dist-info/METADATA
apikeeper-0.0.1.dist-info/RECORD
apikeeper-0.0.1.dist-info/WHEEL
apikeeper-0.0.1.dist-info/top_level.txt
