Metadata-Version: 2.1
Name: apikeeper
Version: 0.0.1
Summary: Open source API gateway, asynchronous sexy and simple.
Home-page: https://github.com/apikeeper/apikeeper
Author: David Silva
Author-email: inonjs@gmail.com
Maintainer: David Silva
Maintainer-email: inonjs@gmail.com
License: MIT license
Keywords: apikeeper
Platform: UNKNOWN
Classifier: Development Status :: 3 - Alpha
Classifier: Intended Audience :: Developers
Classifier: Programming Language :: Python :: 3.6
